{
	"partitions" : [
		{
			"name" : "Top",
			"pins" : [
				{
					"name" : "op[0]",
					"strict" : false
				},
				{
					"name" : "op[1]",
					"strict" : false
				},
				{
					"name" : "op[2]",
					"strict" : false
				},
				{
					"name" : "op[3]",
					"strict" : false
				},
				{
					"name" : "instr[15]",
					"strict" : false
				},
				{
					"name" : "instr[4]",
					"strict" : false
				},
				{
					"name" : "instr[14]",
					"strict" : false
				},
				{
					"name" : "instr[5]",
					"strict" : false
				},
				{
					"name" : "instr[6]",
					"strict" : false
				},
				{
					"name" : "instr[7]",
					"strict" : false
				}
			]
		}
	]
}